bux/__init__.py
bux/__main__.py
bux/_cli.py
bux/_config.py
bux/_guest.py
bux/_request.py
bux/_securities.py
bux/_security.py
bux/_user.py
bux/_ws.py
bux/_commands/__init__.py
bux/_commands/_base.py
bux/_commands/_categories.py
bux/_commands/_countries.py
bux/_commands/_following.py
bux/_commands/_gainers.py
bux/_commands/_get_token.py
bux/_commands/_graph.py
bux/_commands/_inbox.py
bux/_commands/_info.py
bux/_commands/_listen_quotes.py
bux/_commands/_losers.py
bux/_commands/_me.py
bux/_commands/_new_stocks.py
bux/_commands/_orders_config.py
bux/_commands/_search.py
bux/_commands/_tag.py
bux/_commands/_tags.py
bux/_commands/_version.py
bux/types/__init__.py
bux/types/_filter.py
bux/types/_following.py
bux/types/_market_hours.py
bux/types/_me.py
bux/types/_message.py
bux/types/_movers.py
bux/types/_order.py
bux/types/_orders_config.py
bux/types/_personal_data.py
bux/types/_portfolio.py
bux/types/_position.py
bux/types/_price.py
bux/types/_response.py
bux/types/_search.py
bux/types/_sec_graph.py
bux/types/_sec_presentation.py
bux/types/_sec_stats.py
bux/types/_security.py
bux/types/_tag.py
bux/types/_tag_matches.py
bux/types/_ws.py
bux/types/_ws_order.py
bux-0.2.0.dist-info/LICENSE
bux-0.2.0.dist-info/WHEEL
bux-0.2.0.dist-info/METADATA
bux-0.2.0.dist-info/RECORD
