Metadata-Version: 2.1
Name: bux
Version: 0.2.0
Summary: Unofficial SDK and CLI for BUX Zero API.
Home-page: https://github.com/orsinium-labs/bux
License: MIT
Keywords: bux,stocks,finance,api
Author: Gram
Author-email: gram@orsinium.dev
Requires-Python: >=3.7
Classifier: Development Status :: 4 - Beta
Classifier: Environment :: Plugins
Classifier: Intended Audience :: Developers
Classifier: Intended Audience :: Financial and Insurance Industry
Classifier: License :: OSI Approved :: MIT License
Classifier: Programming Language :: Python
Classifier: Topic :: Office/Business :: Financial :: Investment
Classifier: Topic :: Software Development
Classifier: Topic :: Software Development :: Libraries :: Python Modules
Requires-Dist: pytest ; extra == "test"
Requires-Dist: pytest-cov ; extra == "test"
Requires-Dist: vcrpy ; extra == "test"
Provides-Extra: test
